{
  "firstLayout": "",
  "gdVersion": {
    "build": 98,
    "major": 4,
    "minor": 0,
    "revision": 0
  },
  "properties": {
    "adMobAppId": "",
    "adaptGameResolutionAtRuntime": true,
    "folderProject": false,
    "linuxExecutableFilename": "",
    "macExecutableFilename": "",
    "orientation": "landscape",
    "packageName": "com.example.gamename",
    "projectFile": "C:\\Users\\szoszo\\Desktop\\Projects\\GDevelop5\\simple-inventory-system\\game.json",
    "scaleMode": "linear",
    "sizeOnStartupMode": "adaptWidth",
    "useExternalSourceFiles": false,
    "version": "1.0.0",
    "winExecutableFilename": "",
    "winExecutableIconFile": "",
    "name": "Project",
    "author": "@ddabrahim gametemplates.itch.io",
    "windowWidth": 800,
    "windowHeight": 600,
    "latestCompilationDirectory": "",
    "maxFPS": 60,
    "minFPS": 20,
    "verticalSync": false,
    "platformSpecificAssets": {},
    "loadingScreen": {
      "showGDevelopSplash": true
    },
    "extensions": [
      {
        "name": "BuiltinObject"
      },
      {
        "name": "BuiltinAudio"
      },
      {
        "name": "BuiltinVariables"
      },
      {
        "name": "BuiltinTime"
      },
      {
        "name": "BuiltinMouse"
      },
      {
        "name": "BuiltinKeyboard"
      },
      {
        "name": "BuiltinJoystick"
      },
      {
        "name": "BuiltinCamera"
      },
      {
        "name": "BuiltinWindow"
      },
      {
        "name": "BuiltinFile"
      },
      {
        "name": "BuiltinNetwork"
      },
      {
        "name": "BuiltinScene"
      },
      {
        "name": "BuiltinAdvanced"
      },
      {
        "name": "Sprite"
      },
      {
        "name": "BuiltinCommonInstructions"
      },
      {
        "name": "BuiltinCommonConversions"
      },
      {
        "name": "BuiltinStringInstructions"
      },
      {
        "name": "BuiltinMathematicalTools"
      },
      {
        "name": "BuiltinExternalLayouts"
      }
    ],
    "platforms": [
      {
        "name": "GDevelop JS platform"
      }
    ],
    "currentPlatform": "GDevelop JS platform"
  },
  "resources": {
    "resources": [
      {
        "alwaysLoaded": false,
        "file": "images/inventory_empty.png",
        "kind": "image",
        "metadata": "",
        "name": "images\\inventory_empty.png",
        "smoothed": true,
        "userAdded": true
      },
      {
        "alwaysLoaded": false,
        "file": "images/inventory_apple.png",
        "kind": "image",
        "metadata": "",
        "name": "images\\inventory_apple.png",
        "smoothed": true,
        "userAdded": true
      },
      {
        "alwaysLoaded": false,
        "file": "images/inventory_banana.png",
        "kind": "image",
        "metadata": "",
        "name": "images\\inventory_banana.png",
        "smoothed": true,
        "userAdded": true
      },
      {
        "alwaysLoaded": false,
        "file": "images/inventory_cherry.png",
        "kind": "image",
        "metadata": "",
        "name": "images\\inventory_cherry.png",
        "smoothed": true,
        "userAdded": true
      },
      {
        "alwaysLoaded": false,
        "file": "images/inventory_grape.png",
        "kind": "image",
        "metadata": "",
        "name": "images\\inventory_grape.png",
        "smoothed": true,
        "userAdded": true
      },
      {
        "alwaysLoaded": false,
        "file": "images/inventory_orange.png",
        "kind": "image",
        "metadata": "",
        "name": "images\\inventory_orange.png",
        "smoothed": true,
        "userAdded": true
      },
      {
        "alwaysLoaded": false,
        "file": "images/inventory_pearl.png",
        "kind": "image",
        "metadata": "",
        "name": "images\\inventory_pearl.png",
        "smoothed": true,
        "userAdded": true
      },
      {
        "alwaysLoaded": false,
        "file": "images/apple.png",
        "kind": "image",
        "metadata": "",
        "name": "images\\apple.png",
        "smoothed": true,
        "userAdded": true
      },
      {
        "alwaysLoaded": false,
        "file": "images/banana.png",
        "kind": "image",
        "metadata": "",
        "name": "images\\banana.png",
        "smoothed": true,
        "userAdded": true
      },
      {
        "alwaysLoaded": false,
        "file": "images/cherry.png",
        "kind": "image",
        "metadata": "",
        "name": "images\\cherry.png",
        "smoothed": true,
        "userAdded": true
      },
      {
        "alwaysLoaded": false,
        "file": "images/grape.png",
        "kind": "image",
        "metadata": "",
        "name": "images\\grape.png",
        "smoothed": true,
        "userAdded": true
      },
      {
        "alwaysLoaded": false,
        "file": "images/orange.png",
        "kind": "image",
        "metadata": "",
        "name": "images\\orange.png",
        "smoothed": true,
        "userAdded": true
      },
      {
        "alwaysLoaded": false,
        "file": "images/pearl.png",
        "kind": "image",
        "metadata": "",
        "name": "images\\pearl.png",
        "smoothed": true,
        "userAdded": false
      },
      {
        "alwaysLoaded": false,
        "file": "images/inventory_raspberry.png",
        "kind": "image",
        "metadata": "",
        "name": "images\\inventory_raspberry.png",
        "smoothed": true,
        "userAdded": true
      },
      {
        "alwaysLoaded": false,
        "file": "images/inventory_strawberry.png",
        "kind": "image",
        "metadata": "",
        "name": "images\\inventory_strawberry.png",
        "smoothed": true,
        "userAdded": true
      },
      {
        "alwaysLoaded": false,
        "file": "images/inventory_watermelon.png",
        "kind": "image",
        "metadata": "",
        "name": "images\\inventory_watermelon.png",
        "smoothed": true,
        "userAdded": true
      },
      {
        "alwaysLoaded": false,
        "file": "images/raspberry.png",
        "kind": "image",
        "metadata": "",
        "name": "images\\raspberry.png",
        "smoothed": true,
        "userAdded": true
      },
      {
        "alwaysLoaded": false,
        "file": "images/strawberry.png",
        "kind": "image",
        "metadata": "",
        "name": "images\\strawberry.png",
        "smoothed": true,
        "userAdded": true
      },
      {
        "alwaysLoaded": false,
        "file": "images/watermelon.png",
        "kind": "image",
        "metadata": "",
        "name": "images\\watermelon.png",
        "smoothed": true,
        "userAdded": true
      }
    ],
    "resourceFolders": []
  },
  "objects": [],
  "objectsGroups": [],
  "variables": [],
  "layouts": [
    {
      "b": 209,
      "disableInputWhenNotFocused": true,
      "mangledName": "NewScene",
      "name": "NewScene",
      "oglFOV": 90,
      "oglZFar": 500,
      "oglZNear": 1,
      "r": 209,
      "standardSortMethod": true,
      "stopSoundsOnStartup": true,
      "title": "",
      "v": 209,
      "uiSettings": {
        "grid": false,
        "gridB": 255,
        "gridG": 180,
        "gridHeight": 32,
        "gridOffsetX": 0,
        "gridOffsetY": 0,
        "gridR": 158,
        "gridWidth": 32,
        "snap": false,
        "windowMask": false,
        "zoomFactor": 1
      },
      "objectsGroups": [],
      "variables": [],
      "instances": [
        {
          "angle": 0,
          "customSize": false,
          "height": 0,
          "layer": "",
          "locked": false,
          "name": "Slot",
          "width": 0,
          "x": 465,
          "y": 124,
          "zOrder": 1,
          "numberProperties": [],
          "stringProperties": [],
          "initialVariables": []
        },
        {
          "angle": 0,
          "customSize": false,
          "height": 0,
          "layer": "",
          "locked": false,
          "name": "Slot",
          "width": 0,
          "x": 273,
          "y": 124,
          "zOrder": 1,
          "numberProperties": [],
          "stringProperties": [],
          "initialVariables": []
        },
        {
          "angle": 0,
          "customSize": false,
          "height": 0,
          "layer": "",
          "locked": false,
          "name": "Slot",
          "width": 0,
          "x": 369,
          "y": 124,
          "zOrder": 1,
          "numberProperties": [],
          "stringProperties": [],
          "initialVariables": []
        },
        {
          "angle": 0,
          "customSize": false,
          "height": 0,
          "layer": "",
          "locked": false,
          "name": "Item",
          "width": 0,
          "x": 450,
          "y": 288,
          "zOrder": 2,
          "numberProperties": [
            {
              "name": "animation",
              "value": 5
            }
          ],
          "stringProperties": [],
          "initialVariables": []
        },
        {
          "angle": 0,
          "customSize": false,
          "height": 0,
          "layer": "",
          "locked": false,
          "name": "Item",
          "width": 0,
          "x": 130,
          "y": 288,
          "zOrder": 2,
          "numberProperties": [
            {
              "name": "animation",
              "value": 0
            }
          ],
          "stringProperties": [],
          "initialVariables": []
        },
        {
          "angle": 0,
          "customSize": false,
          "height": 0,
          "layer": "",
          "locked": false,
          "name": "Item",
          "width": 0,
          "x": 194,
          "y": 288,
          "zOrder": 2,
          "numberProperties": [
            {
              "name": "animation",
              "value": 1
            }
          ],
          "stringProperties": [],
          "initialVariables": []
        },
        {
          "angle": 0,
          "customSize": false,
          "height": 0,
          "layer": "",
          "locked": false,
          "name": "Item",
          "width": 0,
          "x": 258,
          "y": 288,
          "zOrder": 2,
          "numberProperties": [
            {
              "name": "animation",
              "value": 2
            }
          ],
          "stringProperties": [],
          "initialVariables": []
        },
        {
          "angle": 0,
          "customSize": false,
          "height": 0,
          "layer": "",
          "locked": false,
          "name": "Item",
          "width": 0,
          "x": 322,
          "y": 288,
          "zOrder": 2,
          "numberProperties": [
            {
              "name": "animation",
              "value": 3
            }
          ],
          "stringProperties": [],
          "initialVariables": []
        },
        {
          "angle": 0,
          "customSize": false,
          "height": 0,
          "layer": "",
          "locked": false,
          "name": "Item",
          "width": 0,
          "x": 386,
          "y": 288,
          "zOrder": 2,
          "numberProperties": [
            {
              "name": "animation",
              "value": 4
            }
          ],
          "stringProperties": [],
          "initialVariables": []
        },
        {
          "angle": 0,
          "customSize": false,
          "height": 0,
          "layer": "",
          "locked": false,
          "name": "InventoryText",
          "width": 0,
          "x": 329,
          "y": 58,
          "zOrder": 3,
          "numberProperties": [],
          "stringProperties": [],
          "initialVariables": []
        },
        {
          "angle": 0,
          "customSize": false,
          "height": 0,
          "layer": "",
          "locked": false,
          "name": "ItemsText",
          "width": 0,
          "x": 260,
          "y": 235,
          "zOrder": 4,
          "numberProperties": [],
          "stringProperties": [],
          "initialVariables": []
        },
        {
          "angle": 0,
          "customSize": false,
          "height": 0,
          "layer": "",
          "locked": false,
          "name": "Item",
          "width": 0,
          "x": 514,
          "y": 288,
          "zOrder": 5,
          "numberProperties": [
            {
              "name": "animation",
              "value": 6
            }
          ],
          "stringProperties": [],
          "initialVariables": []
        },
        {
          "angle": 0,
          "customSize": false,
          "height": 0,
          "layer": "",
          "locked": false,
          "name": "Item",
          "width": 0,
          "x": 578,
          "y": 288,
          "zOrder": 6,
          "numberProperties": [
            {
              "name": "animation",
              "value": 7
            }
          ],
          "stringProperties": [],
          "initialVariables": []
        },
        {
          "angle": 0,
          "customSize": false,
          "height": 0,
          "layer": "",
          "locked": false,
          "name": "Item",
          "width": 0,
          "x": 642,
          "y": 288,
          "zOrder": 7,
          "numberProperties": [
            {
              "name": "animation",
              "value": 8
            }
          ],
          "stringProperties": [],
          "initialVariables": []
        },
        {
          "angle": 0,
          "customSize": false,
          "height": 0,
          "layer": "",
          "locked": false,
          "name": "InventoryMessage",
          "width": 0,
          "x": 274,
          "y": 86,
          "zOrder": 8,
          "numberProperties": [],
          "stringProperties": [],
          "initialVariables": []
        }
      ],
      "objects": [
        {
          "name": "Slot",
          "tags": "",
          "type": "Sprite",
          "updateIfNotVisible": false,
          "variables": [],
          "behaviors": [],
          "animations": [
            {
              "name": "Empty",
              "useMultipleDirections": false,
              "directions": [
                {
                  "looping": false,
                  "timeBetweenFrames": 0.08,
                  "sprites": [
                    {
                      "hasCustomCollisionMask": false,
                      "image": "images\\inventory_empty.png",
                      "points": [],
                      "originPoint": {
                        "name": "origine",
                        "x": 0,
                        "y": 0
                      },
                      "centerPoint": {
                        "automatic": true,
                        "name": "centre",
                        "x": 0,
                        "y": 0
                      },
                      "customCollisionMask": []
                    }
                  ]
                }
              ]
            },
            {
              "name": "Apple",
              "useMultipleDirections": false,
              "directions": [
                {
                  "looping": false,
                  "timeBetweenFrames": 0.08,
                  "sprites": [
                    {
                      "hasCustomCollisionMask": false,
                      "image": "images\\inventory_apple.png",
                      "points": [],
                      "originPoint": {
                        "name": "origine",
                        "x": 0,
                        "y": 0
                      },
                      "centerPoint": {
                        "automatic": true,
                        "name": "centre",
                        "x": 0,
                        "y": 0
                      },
                      "customCollisionMask": []
                    }
                  ]
                }
              ]
            },
            {
              "name": "Banana",
              "useMultipleDirections": false,
              "directions": [
                {
                  "looping": false,
                  "timeBetweenFrames": 0.08,
                  "sprites": [
                    {
                      "hasCustomCollisionMask": false,
                      "image": "images\\inventory_banana.png",
                      "points": [],
                      "originPoint": {
                        "name": "origine",
                        "x": 0,
                        "y": 0
                      },
                      "centerPoint": {
                        "automatic": true,
                        "name": "centre",
                        "x": 0,
                        "y": 0
                      },
                      "customCollisionMask": []
                    }
                  ]
                }
              ]
            },
            {
              "name": "Cherry",
              "useMultipleDirections": false,
              "directions": [
                {
                  "looping": false,
                  "timeBetweenFrames": 0.08,
                  "sprites": [
                    {
                      "hasCustomCollisionMask": false,
                      "image": "images\\inventory_cherry.png",
                      "points": [],
                      "originPoint": {
                        "name": "origine",
                        "x": 0,
                        "y": 0
                      },
                      "centerPoint": {
                        "automatic": true,
                        "name": "centre",
                        "x": 0,
                        "y": 0
                      },
                      "customCollisionMask": []
                    }
                  ]
                }
              ]
            },
            {
              "name": "Grape",
              "useMultipleDirections": false,
              "directions": [
                {
                  "looping": false,
                  "timeBetweenFrames": 0.08,
                  "sprites": [
                    {
                      "hasCustomCollisionMask": false,
                      "image": "images\\inventory_grape.png",
                      "points": [],
                      "originPoint": {
                        "name": "origine",
                        "x": 0,
                        "y": 0
                      },
                      "centerPoint": {
                        "automatic": true,
                        "name": "centre",
                        "x": 0,
                        "y": 0
                      },
                      "customCollisionMask": []
                    }
                  ]
                }
              ]
            },
            {
              "name": "Orange",
              "useMultipleDirections": false,
              "directions": [
                {
                  "looping": false,
                  "timeBetweenFrames": 0.08,
                  "sprites": [
                    {
                      "hasCustomCollisionMask": false,
                      "image": "images\\inventory_orange.png",
                      "points": [],
                      "originPoint": {
                        "name": "origine",
                        "x": 0,
                        "y": 0
                      },
                      "centerPoint": {
                        "automatic": true,
                        "name": "centre",
                        "x": 0,
                        "y": 0
                      },
                      "customCollisionMask": []
                    }
                  ]
                }
              ]
            },
            {
              "name": "Pearl",
              "useMultipleDirections": false,
              "directions": [
                {
                  "looping": false,
                  "timeBetweenFrames": 0.08,
                  "sprites": [
                    {
                      "hasCustomCollisionMask": false,
                      "image": "images\\inventory_pearl.png",
                      "points": [],
                      "originPoint": {
                        "name": "origine",
                        "x": 0,
                        "y": 0
                      },
                      "centerPoint": {
                        "automatic": true,
                        "name": "centre",
                        "x": 0,
                        "y": 0
                      },
                      "customCollisionMask": []
                    }
                  ]
                }
              ]
            },
            {
              "name": "Raspberry",
              "useMultipleDirections": false,
              "directions": [
                {
                  "looping": false,
                  "timeBetweenFrames": 0.08,
                  "sprites": [
                    {
                      "hasCustomCollisionMask": false,
                      "image": "images\\inventory_raspberry.png",
                      "points": [],
                      "originPoint": {
                        "name": "origine",
                        "x": 0,
                        "y": 0
                      },
                      "centerPoint": {
                        "automatic": true,
                        "name": "centre",
                        "x": 0,
                        "y": 0
                      },
                      "customCollisionMask": []
                    }
                  ]
                }
              ]
            },
            {
              "name": "Strawberry",
              "useMultipleDirections": false,
              "directions": [
                {
                  "looping": false,
                  "timeBetweenFrames": 0.08,
                  "sprites": [
                    {
                      "hasCustomCollisionMask": false,
                      "image": "images\\inventory_strawberry.png",
                      "points": [],
                      "originPoint": {
                        "name": "origine",
                        "x": 0,
                        "y": 0
                      },
                      "centerPoint": {
                        "automatic": true,
                        "name": "centre",
                        "x": 0,
                        "y": 0
                      },
                      "customCollisionMask": []
                    }
                  ]
                }
              ]
            },
            {
              "name": "Watermelon",
              "useMultipleDirections": false,
              "directions": [
                {
                  "looping": false,
                  "timeBetweenFrames": 0.08,
                  "sprites": [
                    {
                      "hasCustomCollisionMask": false,
                      "image": "images\\inventory_watermelon.png",
                      "points": [],
                      "originPoint": {
                        "name": "origine",
                        "x": 0,
                        "y": 0
                      },
                      "centerPoint": {
                        "automatic": true,
                        "name": "centre",
                        "x": 0,
                        "y": 0
                      },
                      "customCollisionMask": []
                    }
                  ]
                }
              ]
            }
          ]
        },
        {
          "name": "Item",
          "tags": "",
          "type": "Sprite",
          "updateIfNotVisible": false,
          "variables": [],
          "behaviors": [],
          "animations": [
            {
              "name": "Apple",
              "useMultipleDirections": false,
              "directions": [
                {
                  "looping": false,
                  "timeBetweenFrames": 0.08,
                  "sprites": [
                    {
                      "hasCustomCollisionMask": false,
                      "image": "images\\apple.png",
                      "points": [],
                      "originPoint": {
                        "name": "origine",
                        "x": 0,
                        "y": 0
                      },
                      "centerPoint": {
                        "automatic": true,
                        "name": "centre",
                        "x": 0,
                        "y": 0
                      },
                      "customCollisionMask": []
                    }
                  ]
                }
              ]
            },
            {
              "name": "Banana",
              "useMultipleDirections": false,
              "directions": [
                {
                  "looping": false,
                  "timeBetweenFrames": 0.08,
                  "sprites": [
                    {
                      "hasCustomCollisionMask": false,
                      "image": "images\\banana.png",
                      "points": [],
                      "originPoint": {
                        "name": "origine",
                        "x": 0,
                        "y": 0
                      },
                      "centerPoint": {
                        "automatic": true,
                        "name": "centre",
                        "x": 0,
                        "y": 0
                      },
                      "customCollisionMask": []
                    }
                  ]
                }
              ]
            },
            {
              "name": "Cherry",
              "useMultipleDirections": false,
              "directions": [
                {
                  "looping": false,
                  "timeBetweenFrames": 0.08,
                  "sprites": [
                    {
                      "hasCustomCollisionMask": false,
                      "image": "images\\cherry.png",
                      "points": [],
                      "originPoint": {
                        "name": "origine",
                        "x": 0,
                        "y": 0
                      },
                      "centerPoint": {
                        "automatic": true,
                        "name": "centre",
                        "x": 0,
                        "y": 0
                      },
                      "customCollisionMask": []
                    }
                  ]
                }
              ]
            },
            {
              "name": "Grape",
              "useMultipleDirections": false,
              "directions": [
                {
                  "looping": false,
                  "timeBetweenFrames": 0.08,
                  "sprites": [
                    {
                      "hasCustomCollisionMask": false,
                      "image": "images\\grape.png",
                      "points": [],
                      "originPoint": {
                        "name": "origine",
                        "x": 0,
                        "y": 0
                      },
                      "centerPoint": {
                        "automatic": true,
                        "name": "centre",
                        "x": 0,
                        "y": 0
                      },
                      "customCollisionMask": []
                    }
                  ]
                }
              ]
            },
            {
              "name": "Orange",
              "useMultipleDirections": false,
              "directions": [
                {
                  "looping": false,
                  "timeBetweenFrames": 0.08,
                  "sprites": [
                    {
                      "hasCustomCollisionMask": false,
                      "image": "images\\orange.png",
                      "points": [],
                      "originPoint": {
                        "name": "origine",
                        "x": 0,
                        "y": 0
                      },
                      "centerPoint": {
                        "automatic": true,
                        "name": "centre",
                        "x": 0,
                        "y": 0
                      },
                      "customCollisionMask": []
                    }
                  ]
                }
              ]
            },
            {
              "name": "Pearl",
              "useMultipleDirections": false,
              "directions": [
                {
                  "looping": false,
                  "timeBetweenFrames": 0.08,
                  "sprites": [
                    {
                      "hasCustomCollisionMask": false,
                      "image": "images\\pearl.png",
                      "points": [],
                      "originPoint": {
                        "name": "origine",
                        "x": 0,
                        "y": 0
                      },
                      "centerPoint": {
                        "automatic": true,
                        "name": "centre",
                        "x": 0,
                        "y": 0
                      },
                      "customCollisionMask": []
                    }
                  ]
                }
              ]
            },
            {
              "name": "Raspberry",
              "useMultipleDirections": false,
              "directions": [
                {
                  "looping": false,
                  "timeBetweenFrames": 0.08,
                  "sprites": [
                    {
                      "hasCustomCollisionMask": false,
                      "image": "images\\raspberry.png",
                      "points": [],
                      "originPoint": {
                        "name": "origine",
                        "x": 0,
                        "y": 0
                      },
                      "centerPoint": {
                        "automatic": true,
                        "name": "centre",
                        "x": 0,
                        "y": 0
                      },
                      "customCollisionMask": []
                    }
                  ]
                }
              ]
            },
            {
              "name": "Strawberry",
              "useMultipleDirections": false,
              "directions": [
                {
                  "looping": false,
                  "timeBetweenFrames": 0.08,
                  "sprites": [
                    {
                      "hasCustomCollisionMask": false,
                      "image": "images\\strawberry.png",
                      "points": [],
                      "originPoint": {
                        "name": "origine",
                        "x": 0,
                        "y": 0
                      },
                      "centerPoint": {
                        "automatic": true,
                        "name": "centre",
                        "x": 0,
                        "y": 0
                      },
                      "customCollisionMask": []
                    }
                  ]
                }
              ]
            },
            {
              "name": "Watermelon",
              "useMultipleDirections": false,
              "directions": [
                {
                  "looping": false,
                  "timeBetweenFrames": 0.08,
                  "sprites": [
                    {
                      "hasCustomCollisionMask": false,
                      "image": "images\\watermelon.png",
                      "points": [],
                      "originPoint": {
                        "name": "origine",
                        "x": 0,
                        "y": 0
                      },
                      "centerPoint": {
                        "automatic": true,
                        "name": "centre",
                        "x": 0,
                        "y": 0
                      },
                      "customCollisionMask": []
                    }
                  ]
                }
              ]
            }
          ]
        },
        {
          "bold": true,
          "italic": false,
          "name": "InventoryText",
          "smoothed": true,
          "tags": "",
          "type": "TextObject::Text",
          "underlined": false,
          "variables": [],
          "behaviors": [],
          "string": "Inventory Slots",
          "font": "",
          "characterSize": 20,
          "color": {
            "b": 0,
            "g": 0,
            "r": 0
          }
        },
        {
          "bold": false,
          "italic": false,
          "name": "ItemsText",
          "smoothed": true,
          "tags": "",
          "type": "TextObject::Text",
          "underlined": false,
          "variables": [],
          "behaviors": [],
          "string": "Click an item to add to inventory",
          "font": "",
          "characterSize": 20,
          "color": {
            "b": 0,
            "g": 0,
            "r": 0
          }
        },
        {
          "bold": false,
          "italic": false,
          "name": "InventoryMessage",
          "smoothed": true,
          "tags": "",
          "type": "TextObject::Text",
          "underlined": false,
          "variables": [],
          "behaviors": [],
          "string": "Click slot to Use/Delete item",
          "font": "",
          "characterSize": 20,
          "color": {
            "b": 0,
            "g": 0,
            "r": 0
          }
        }
      ],
      "events": [
        {
          "disabled": false,
          "folded": false,
          "type": "BuiltinCommonInstructions::Comment",
          "color": {
            "b": 109,
            "g": 230,
            "r": 255,
            "textB": 0,
            "textG": 0,
            "textR": 0
          },
          "comment": "for more examples and templates visit gametemplates.itch.io",
          "comment2": ""
        },
        {
          "colorB": 228,
          "colorG": 176,
          "colorR": 74,
          "creationTime": 0,
          "disabled": false,
          "folded": false,
          "name": "Initialize",
          "source": "",
          "type": "BuiltinCommonInstructions::Group",
          "events": [
            {
              "disabled": false,
              "folded": false,
              "type": "BuiltinCommonInstructions::Comment",
              "color": {
                "b": 109,
                "g": 230,
                "r": 255,
                "textB": 0,
                "textG": 0,
                "textR": 0
              },
              "comment": "At the beginning of the scene, initialize a scene variable with the value \"No\" to flag we did not have an item picked",
              "comment2": ""
            },
            {
              "disabled": false,
              "folded": false,
              "type": "BuiltinCommonInstructions::Standard",
              "conditions": [
                {
                  "type": {
                    "inverted": false,
                    "value": "DepartScene"
                  },
                  "parameters": [
                    "itemPicked"
                  ],
                  "subInstructions": []
                }
              ],
              "actions": [
                {
                  "type": {
                    "inverted": false,
                    "value": "ModVarSceneTxt"
                  },
                  "parameters": [
                    "itemPicked",
                    "=",
                    "\"No\""
                  ],
                  "subInstructions": []
                }
              ],
              "events": []
            }
          ],
          "parameters": []
        },
        {
          "colorB": 228,
          "colorG": 176,
          "colorR": 74,
          "creationTime": 0,
          "disabled": false,
          "folded": false,
          "name": "Collect item and add to inventory",
          "source": "",
          "type": "BuiltinCommonInstructions::Group",
          "events": [
            {
              "disabled": false,
              "folded": false,
              "type": "BuiltinCommonInstructions::Comment",
              "color": {
                "b": 109,
                "g": 230,
                "r": 255,
                "textB": 0,
                "textG": 0,
                "textR": 0
              },
              "comment": "if mouse is clicked on an item\nSet scene variable itemPicked to \"Yes\" to indicate we have picked an item",
              "comment2": ""
            },
            {
              "disabled": false,
              "folded": false,
              "type": "BuiltinCommonInstructions::Standard",
              "conditions": [
                {
                  "type": {
                    "inverted": false,
                    "value": "SourisBouton"
                  },
                  "parameters": [
                    "",
                    "Left"
                  ],
                  "subInstructions": []
                },
                {
                  "type": {
                    "inverted": false,
                    "value": "SourisSurObjet"
                  },
                  "parameters": [
                    "Item",
                    "",
                    "",
                    ""
                  ],
                  "subInstructions": []
                }
              ],
              "actions": [
                {
                  "type": {
                    "inverted": false,
                    "value": "ModVarSceneTxt"
                  },
                  "parameters": [
                    "itemPicked",
                    "=",
                    "\"Yes\""
                  ],
                  "subInstructions": []
                }
              ],
              "events": [
                {
                  "disabled": false,
                  "folded": false,
                  "type": "BuiltinCommonInstructions::Comment",
                  "color": {
                    "b": 109,
                    "g": 230,
                    "r": 255,
                    "textB": 0,
                    "textG": 0,
                    "textR": 0
                  },
                  "comment": "Repeat for each slot one by one, Note the for each event\nCheck if the animation of the slot is \"Empty\"\nCheck the scene variable itemPicked if the value is still \"Yes\"\nThe action going to fire only if the slot is empty and the value is \"Yes\"\nThen execute the action to set the animation of the slot to be the same as the animation of the item using Animation name.\nDelete the item\nSet the scene variable itemPicked back to \"No\" to indicate we no longer have any item picked\nEven if there is more free slots, the action will no longer execute until we click an item again\nIf there is no Empty slot, no action is going to execute",
                  "comment2": ""
                },
                {
                  "disabled": false,
                  "folded": false,
                  "type": "BuiltinCommonInstructions::ForEach",
                  "object": "Slot",
                  "conditions": [
                    {
                      "type": {
                        "inverted": false,
                        "value": "VarSceneTxt"
                      },
                      "parameters": [
                        "itemPicked",
                        "=",
                        "\"Yes\""
                      ],
                      "subInstructions": []
                    },
                    {
                      "type": {
                        "inverted": false,
                        "value": "AnimationName"
                      },
                      "parameters": [
                        "Slot",
                        "\"Empty\""
                      ],
                      "subInstructions": []
                    }
                  ],
                  "actions": [
                    {
                      "type": {
                        "inverted": false,
                        "value": "SetAnimationName"
                      },
                      "parameters": [
                        "Slot",
                        "Item.AnimationName()"
                      ],
                      "subInstructions": []
                    },
                    {
                      "type": {
                        "inverted": false,
                        "value": "Delete"
                      },
                      "parameters": [
                        "Item",
                        ""
                      ],
                      "subInstructions": []
                    },
                    {
                      "type": {
                        "inverted": false,
                        "value": "ModVarSceneTxt"
                      },
                      "parameters": [
                        "itemPicked",
                        "=",
                        "\"No\""
                      ],
                      "subInstructions": []
                    }
                  ],
                  "events": []
                }
              ]
            }
          ],
          "parameters": []
        },
        {
          "colorB": 228,
          "colorG": 176,
          "colorR": 74,
          "creationTime": 0,
          "disabled": false,
          "folded": false,
          "name": "Delete/Use item from inventory",
          "source": "",
          "type": "BuiltinCommonInstructions::Group",
          "events": [
            {
              "disabled": false,
              "folded": false,
              "type": "BuiltinCommonInstructions::Comment",
              "color": {
                "b": 109,
                "g": 230,
                "r": 255,
                "textB": 0,
                "textG": 0,
                "textR": 0
              },
              "comment": "If mouse button is clicked on a slot and the animation of the slot is NOT Empty, then use the the item\n",
              "comment2": ""
            },
            {
              "disabled": false,
              "folded": false,
              "type": "BuiltinCommonInstructions::Standard",
              "conditions": [
                {
                  "type": {
                    "inverted": false,
                    "value": "SourisBouton"
                  },
                  "parameters": [
                    "",
                    "Left"
                  ],
                  "subInstructions": []
                },
                {
                  "type": {
                    "inverted": false,
                    "value": "SourisSurObjet"
                  },
                  "parameters": [
                    "Slot",
                    "",
                    "",
                    ""
                  ],
                  "subInstructions": []
                }
              ],
              "actions": [],
              "events": [
                {
                  "disabled": false,
                  "folded": false,
                  "type": "BuiltinCommonInstructions::Comment",
                  "color": {
                    "b": 109,
                    "g": 230,
                    "r": 255,
                    "textB": 0,
                    "textG": 0,
                    "textR": 0
                  },
                  "comment": "Check the animation of the slot to see what it is, \nIf it is an Apple, you want to add the action here what to do if you use an Apple, for example increase health.\nYou want to add an event like this for all possible animations.\nWe did not implement this in this example, it is only to demonstrate where and how you can do it",
                  "comment2": ""
                },
                {
                  "disabled": false,
                  "folded": false,
                  "type": "BuiltinCommonInstructions::Standard",
                  "conditions": [
                    {
                      "type": {
                        "inverted": false,
                        "value": "AnimationName"
                      },
                      "parameters": [
                        "Slot",
                        "\"Apple\""
                      ],
                      "subInstructions": []
                    }
                  ],
                  "actions": [],
                  "events": []
                },
                {
                  "disabled": false,
                  "folded": false,
                  "type": "BuiltinCommonInstructions::Comment",
                  "color": {
                    "b": 109,
                    "g": 230,
                    "r": 255,
                    "textB": 0,
                    "textG": 0,
                    "textR": 0
                  },
                  "comment": "Finally, set the animation back to Empty to indicate the slot is free",
                  "comment2": ""
                },
                {
                  "disabled": false,
                  "folded": false,
                  "type": "BuiltinCommonInstructions::Standard",
                  "conditions": [
                    {
                      "type": {
                        "inverted": true,
                        "value": "AnimationName"
                      },
                      "parameters": [
                        "Slot",
                        "\"Empty\""
                      ],
                      "subInstructions": []
                    }
                  ],
                  "actions": [
                    {
                      "type": {
                        "inverted": false,
                        "value": "SetAnimationName"
                      },
                      "parameters": [
                        "Slot",
                        "\"Empty\""
                      ],
                      "subInstructions": []
                    }
                  ],
                  "events": []
                }
              ]
            }
          ],
          "parameters": []
        }
      ],
      "layers": [
        {
          "name": "",
          "visibility": true,
          "cameras": [
            {
              "defaultSize": true,
              "defaultViewport": true,
              "height": 0,
              "viewportBottom": 1,
              "viewportLeft": 0,
              "viewportRight": 1,
              "viewportTop": 0,
              "width": 0
            }
          ],
          "effects": []
        }
      ],
      "behaviorsSharedData": []
    }
  ],
  "externalEvents": [],
  "eventsFunctionsExtensions": [],
  "externalLayouts": [],
  "externalSourceFiles": []
}